[
  {
    "id": "dl-tag-001",
    "name": "deep",
    "category": "DL",
    "description": "DL标签:deep",
    "count": 0,
    "createdAt": "2026-07-02T00:00:00.000Z"
  },
  {
    "id": "dl-tag-002",
    "name": "learning",
    "category": "DL",
    "description": "DL标签:learning",
    "count": 0,
    "createdAt": "2026-07-02T00:00:00.000Z"
  },
  {
    "id": "dl-tag-003",
    "name": "neural",
    "category": "DL",
    "description": "DL标签:neural",
    "count": 0,
    "createdAt": "2026-07-02T00:00:00.000Z"
  },
  {
    "id": "dl-tag-004",
    "name": "network",
    "category": "DL",
    "description": "DL标签:network",
    "count": 0,
    "createdAt": "2026-07-02T00:00:00.000Z"
  },
  {
    "id": "dl-tag-005",
    "name": "neuron",
    "category": "DL",
    "description": "DL标签:neuron",
    "count": 0,
    "createdAt": "2026-07-02T00:00:00.000Z"
  },
  {
    "id": "dl-tag-006",
    "name": "weight",
    "category": "DL",
    "description": "DL标签:weight",
    "count": 0,
    "createdAt": "2026-07-02T00:00:00.000Z"
  },
  {
    "id": "dl-tag-007",
    "name": "bias",
    "category": "DL",
    "description": "DL标签:bias",
    "count": 0,
    "createdAt": "2026-07-02T00:00:00.000Z"
  },
  {
    "id": "dl-tag-008",
    "name": "tensor",
    "category": "DL",
    "description": "DL标签:tensor",
    "count": 0,
    "createdAt": "2026-07-02T00:00:00.000Z"
  },
  {
    "id": "dl-tag-009",
    "name": "computation",
    "category": "DL",
    "description": "DL标签:computation",
    "count": 0,
    "createdAt": "2026-07-02T00:00:00.000Z"
  },
  {
    "id": "dl-tag-010",
    "name": "graph",
    "category": "DL",
    "description": "DL标签:graph",
    "count": 0,
    "createdAt": "2026-07-02T00:00:00.000Z"
  },
  {
    "id": "dl-tag-011",
    "name": "forward",
    "category": "DL",
    "description": "DL标签:forward",
    "count": 0,
    "createdAt": "2026-07-02T00:00:00.000Z"
  },
  {
    "id": "dl-tag-012",
    "name": "propagation",
    "category": "DL",
    "description": "DL标签:propagation",
    "count": 0,
    "createdAt": "2026-07-02T00:00:00.000Z"
  },
  {
    "id": "dl-tag-013",
    "name": "backward",
    "category": "DL",
    "description": "DL标签:backward",
    "count": 0,
    "createdAt": "2026-07-02T00:00:00.000Z"
  },
  {
    "id": "dl-tag-014",
    "name": "propagation",
    "category": "DL",
    "description": "DL标签:propagation",
    "count": 0,
    "createdAt": "2026-07-02T00:00:00.000Z"
  },
  {
    "id": "dl-tag-015",
    "name": "chain",
    "category": "DL",
    "description": "DL标签:chain",
    "count": 0,
    "createdAt": "2026-07-02T00:00:00.000Z"
  },
  {
    "id": "dl-tag-016",
    "name": "rule",
    "category": "DL",
    "description": "DL标签:rule",
    "count": 0,
    "createdAt": "2026-07-02T00:00:00.000Z"
  },
  {
    "id": "dl-tag-017",
    "name": "gradient",
    "category": "DL",
    "description": "DL标签:gradient",
    "count": 0,
    "createdAt": "2026-07-02T00:00:00.000Z"
  },
  {
    "id": "dl-tag-018",
    "name": "learning",
    "category": "DL",
    "description": "DL标签:learning",
    "count": 0,
    "createdAt": "2026-07-02T00:00:00.000Z"
  },
  {
    "id": "dl-tag-019",
    "name": "rate",
    "category": "DL",
    "description": "DL标签:rate",
    "count": 0,
    "createdAt": "2026-07-02T00:00:00.000Z"
  },
  {
    "id": "dl-tag-020",
    "name": "epoch",
    "category": "DL",
    "description": "DL标签:epoch",
    "count": 0,
    "createdAt": "2026-07-02T00:00:00.000Z"
  },
  {
    "id": "dl-tag-021",
    "name": "batch",
    "category": "DL",
    "description": "DL标签:batch",
    "count": 0,
    "createdAt": "2026-07-02T00:00:00.000Z"
  },
  {
    "id": "dl-tag-022",
    "name": "iteration",
    "category": "DL",
    "description": "DL标签:iteration",
    "count": 0,
    "createdAt": "2026-07-02T00:00:00.000Z"
  },
  {
    "id": "dl-tag-023",
    "name": "activation",
    "category": "DL",
    "description": "DL标签:activation",
    "count": 0,
    "createdAt": "2026-07-02T00:00:00.000Z"
  },
  {
    "id": "dl-tag-024",
    "name": "ReLU",
    "category": "DL",
    "description": "DL标签:ReLU",
    "count": 0,
    "createdAt": "2026-07-02T00:00:00.000Z"
  },
  {
    "id": "dl-tag-025",
    "name": "Sigmoid",
    "category": "DL",
    "description": "DL标签:Sigmoid",
    "count": 0,
    "createdAt": "2026-07-02T00:00:00.000Z"
  },
  {
    "id": "dl-tag-026",
    "name": "Tanh",
    "category": "DL",
    "description": "DL标签:Tanh",
    "count": 0,
    "createdAt": "2026-07-02T00:00:00.000Z"
  },
  {
    "id": "dl-tag-027",
    "name": "Softmax",
    "category": "DL",
    "description": "DL标签:Softmax",
    "count": 0,
    "createdAt": "2026-07-02T00:00:00.000Z"
  },
  {
    "id": "dl-tag-028",
    "name": "loss",
    "category": "DL",
    "description": "DL标签:loss",
    "count": 0,
    "createdAt": "2026-07-02T00:00:00.000Z"
  },
  {
    "id": "dl-tag-029",
    "name": "MSE",
    "category": "DL",
    "description": "DL标签:MSE",
    "count": 0,
    "createdAt": "2026-07-02T00:00:00.000Z"
  },
  {
    "id": "dl-tag-030",
    "name": "CrossEntropy",
    "category": "DL",
    "description": "DL标签:CrossEntropy",
    "count": 0,
    "createdAt": "2026-07-02T00:00:00.000Z"
  },
  {
    "id": "dl-tag-031",
    "name": "optimizer",
    "category": "DL",
    "description": "DL标签:optimizer",
    "count": 0,
    "createdAt": "2026-07-02T00:00:00.000Z"
  },
  {
    "id": "dl-tag-032",
    "name": "SGD",
    "category": "DL",
    "description": "DL标签:SGD",
    "count": 0,
    "createdAt": "2026-07-02T00:00:00.000Z"
  },
  {
    "id": "dl-tag-033",
    "name": "Momentum",
    "category": "DL",
    "description": "DL标签:Momentum",
    "count": 0,
    "createdAt": "2026-07-02T00:00:00.000Z"
  },
  {
    "id": "dl-tag-034",
    "name": "Adam",
    "category": "DL",
    "description": "DL标签:Adam",
    "count": 0,
    "createdAt": "2026-07-02T00:00:00.000Z"
  },
  {
    "id": "dl-tag-035",
    "name": "weight",
    "category": "DL",
    "description": "DL标签:weight",
    "count": 0,
    "createdAt": "2026-07-02T00:00:00.000Z"
  },
  {
    "id": "dl-tag-036",
    "name": "init",
    "category": "DL",
    "description": "DL标签:init",
    "count": 0,
    "createdAt": "2026-07-02T00:00:00.000Z"
  },
  {
    "id": "dl-tag-037",
    "name": "MLP",
    "category": "DL",
    "description": "DL标签:MLP",
    "count": 0,
    "createdAt": "2026-07-02T00:00:00.000Z"
  },
  {
    "id": "dl-tag-038",
    "name": "CNN",
    "category": "DL",
    "description": "DL标签:CNN",
    "count": 0,
    "createdAt": "2026-07-02T00:00:00.000Z"
  },
  {
    "id": "dl-tag-039",
    "name": "convolution",
    "category": "DL",
    "description": "DL标签:convolution",
    "count": 0,
    "createdAt": "2026-07-02T00:00:00.000Z"
  },
  {
    "id": "dl-tag-040",
    "name": "kernel",
    "category": "DL",
    "description": "DL标签:kernel",
    "count": 0,
    "createdAt": "2026-07-02T00:00:00.000Z"
  },
  {
    "id": "dl-tag-041",
    "name": "stride",
    "category": "DL",
    "description": "DL标签:stride",
    "count": 0,
    "createdAt": "2026-07-02T00:00:00.000Z"
  },
  {
    "id": "dl-tag-042",
    "name": "padding",
    "category": "DL",
    "description": "DL标签:padding",
    "count": 0,
    "createdAt": "2026-07-02T00:00:00.000Z"
  },
  {
    "id": "dl-tag-043",
    "name": "pooling",
    "category": "DL",
    "description": "DL标签:pooling",
    "count": 0,
    "createdAt": "2026-07-02T00:00:00.000Z"
  },
  {
    "id": "dl-tag-044",
    "name": "fully",
    "category": "DL",
    "description": "DL标签:fully",
    "count": 0,
    "createdAt": "2026-07-02T00:00:00.000Z"
  },
  {
    "id": "dl-tag-045",
    "name": "connected",
    "category": "DL",
    "description": "DL标签:connected",
    "count": 0,
    "createdAt": "2026-07-02T00:00:00.000Z"
  },
  {
    "id": "dl-tag-046",
    "name": "image",
    "category": "DL",
    "description": "DL标签:image",
    "count": 0,
    "createdAt": "2026-07-02T00:00:00.000Z"
  },
  {
    "id": "dl-tag-047",
    "name": "classification",
    "category": "DL",
    "description": "DL标签:classification",
    "count": 0,
    "createdAt": "2026-07-02T00:00:00.000Z"
  },
  {
    "id": "dl-tag-048",
    "name": "RNN",
    "category": "DL",
    "description": "DL标签:RNN",
    "count": 0,
    "createdAt": "2026-07-02T00:00:00.000Z"
  },
  {
    "id": "dl-tag-049",
    "name": "LSTM",
    "category": "DL",
    "description": "DL标签:LSTM",
    "count": 0,
    "createdAt": "2026-07-02T00:00:00.000Z"
  },
  {
    "id": "dl-tag-050",
    "name": "GRU",
    "category": "DL",
    "description": "DL标签:GRU",
    "count": 0,
    "createdAt": "2026-07-02T00:00:00.000Z"
  },
  {
    "id": "dl-tag-051",
    "name": "sequence",
    "category": "DL",
    "description": "DL标签:sequence",
    "count": 0,
    "createdAt": "2026-07-02T00:00:00.000Z"
  },
  {
    "id": "dl-tag-052",
    "name": "modeling",
    "category": "DL",
    "description": "DL标签:modeling",
    "count": 0,
    "createdAt": "2026-07-02T00:00:00.000Z"
  },
  {
    "id": "dl-tag-053",
    "name": "attention",
    "category": "DL",
    "description": "DL标签:attention",
    "count": 0,
    "createdAt": "2026-07-02T00:00:00.000Z"
  },
  {
    "id": "dl-tag-054",
    "name": "self-attention",
    "category": "DL",
    "description": "DL标签:self-attention",
    "count": 0,
    "createdAt": "2026-07-02T00:00:00.000Z"
  },
  {
    "id": "dl-tag-055",
    "name": "transformer",
    "category": "DL",
    "description": "DL标签:transformer",
    "count": 0,
    "createdAt": "2026-07-02T00:00:00.000Z"
  },
  {
    "id": "dl-tag-056",
    "name": "embedding",
    "category": "DL",
    "description": "DL标签:embedding",
    "count": 0,
    "createdAt": "2026-07-02T00:00:00.000Z"
  },
  {
    "id": "dl-tag-057",
    "name": "position",
    "category": "DL",
    "description": "DL标签:position",
    "count": 0,
    "createdAt": "2026-07-02T00:00:00.000Z"
  },
  {
    "id": "dl-tag-058",
    "name": "encoding",
    "category": "DL",
    "description": "DL标签:encoding",
    "count": 0,
    "createdAt": "2026-07-02T00:00:00.000Z"
  },
  {
    "id": "dl-tag-059",
    "name": "PyTorch",
    "category": "DL",
    "description": "DL标签:PyTorch",
    "count": 0,
    "createdAt": "2026-07-02T00:00:00.000Z"
  },
  {
    "id": "dl-tag-060",
    "name": "autograd",
    "category": "DL",
    "description": "DL标签:autograd",
    "count": 0,
    "createdAt": "2026-07-02T00:00:00.000Z"
  },
  {
    "id": "dl-tag-061",
    "name": "Dataset",
    "category": "DL",
    "description": "DL标签:Dataset",
    "count": 0,
    "createdAt": "2026-07-02T00:00:00.000Z"
  },
  {
    "id": "dl-tag-062",
    "name": "DataLoader",
    "category": "DL",
    "description": "DL标签:DataLoader",
    "count": 0,
    "createdAt": "2026-07-02T00:00:00.000Z"
  },
  {
    "id": "dl-tag-063",
    "name": "training",
    "category": "DL",
    "description": "DL标签:training",
    "count": 0,
    "createdAt": "2026-07-02T00:00:00.000Z"
  },
  {
    "id": "dl-tag-064",
    "name": "loop",
    "category": "DL",
    "description": "DL标签:loop",
    "count": 0,
    "createdAt": "2026-07-02T00:00:00.000Z"
  },
  {
    "id": "dl-tag-065",
    "name": "validation",
    "category": "DL",
    "description": "DL标签:validation",
    "count": 0,
    "createdAt": "2026-07-02T00:00:00.000Z"
  },
  {
    "id": "dl-tag-066",
    "name": "model",
    "category": "DL",
    "description": "DL标签:model",
    "count": 0,
    "createdAt": "2026-07-02T00:00:00.000Z"
  },
  {
    "id": "dl-tag-067",
    "name": "save",
    "category": "DL",
    "description": "DL标签:save",
    "count": 0,
    "createdAt": "2026-07-02T00:00:00.000Z"
  },
  {
    "id": "dl-tag-068",
    "name": "inference",
    "category": "DL",
    "description": "DL标签:inference",
    "count": 0,
    "createdAt": "2026-07-02T00:00:00.000Z"
  },
  {
    "id": "dl-tag-069",
    "name": "GPU",
    "category": "DL",
    "description": "DL标签:GPU",
    "count": 0,
    "createdAt": "2026-07-02T00:00:00.000Z"
  },
  {
    "id": "dl-tag-070",
    "name": "CUDA",
    "category": "DL",
    "description": "DL标签:CUDA",
    "count": 0,
    "createdAt": "2026-07-02T00:00:00.000Z"
  },
  {
    "id": "dl-tag-071",
    "name": "dropout",
    "category": "DL",
    "description": "DL标签:dropout",
    "count": 0,
    "createdAt": "2026-07-02T00:00:00.000Z"
  },
  {
    "id": "dl-tag-072",
    "name": "batchnorm",
    "category": "DL",
    "description": "DL标签:batchnorm",
    "count": 0,
    "createdAt": "2026-07-02T00:00:00.000Z"
  },
  {
    "id": "dl-tag-073",
    "name": "layernorm",
    "category": "DL",
    "description": "DL标签:layernorm",
    "count": 0,
    "createdAt": "2026-07-02T00:00:00.000Z"
  },
  {
    "id": "dl-tag-074",
    "name": "regularization",
    "category": "DL",
    "description": "DL标签:regularization",
    "count": 0,
    "createdAt": "2026-07-02T00:00:00.000Z"
  },
  {
    "id": "dl-tag-075",
    "name": "overfitting",
    "category": "DL",
    "description": "DL标签:overfitting",
    "count": 0,
    "createdAt": "2026-07-02T00:00:00.000Z"
  },
  {
    "id": "dl-tag-076",
    "name": "underfitting",
    "category": "DL",
    "description": "DL标签:underfitting",
    "count": 0,
    "createdAt": "2026-07-02T00:00:00.000Z"
  },
  {
    "id": "dl-tag-077",
    "name": "AlexNet",
    "category": "DL",
    "description": "DL标签:AlexNet",
    "count": 0,
    "createdAt": "2026-07-02T00:00:00.000Z"
  },
  {
    "id": "dl-tag-078",
    "name": "VGG",
    "category": "DL",
    "description": "DL标签:VGG",
    "count": 0,
    "createdAt": "2026-07-02T00:00:00.000Z"
  },
  {
    "id": "dl-tag-079",
    "name": "ResNet",
    "category": "DL",
    "description": "DL标签:ResNet",
    "count": 0,
    "createdAt": "2026-07-02T00:00:00.000Z"
  },
  {
    "id": "dl-tag-080",
    "name": "BERT",
    "category": "DL",
    "description": "DL标签:BERT",
    "count": 0,
    "createdAt": "2026-07-02T00:00:00.000Z"
  },
  {
    "id": "dl-tag-081",
    "name": "GPT",
    "category": "DL",
    "description": "DL标签:GPT",
    "count": 0,
    "createdAt": "2026-07-02T00:00:00.000Z"
  },
  {
    "id": "dl-tag-082",
    "name": "seq2seq",
    "category": "DL",
    "description": "DL标签:seq2seq",
    "count": 0,
    "createdAt": "2026-07-02T00:00:00.000Z"
  },
  {
    "id": "dl-tag-083",
    "name": "attention",
    "category": "DL",
    "description": "DL标签:attention",
    "count": 0,
    "createdAt": "2026-07-02T00:00:00.000Z"
  },
  {
    "id": "dl-tag-084",
    "name": "mechanism",
    "category": "DL",
    "description": "DL标签:mechanism",
    "count": 0,
    "createdAt": "2026-07-02T00:00:00.000Z"
  },
  {
    "id": "dl-tag-085",
    "name": "transformer",
    "category": "DL",
    "description": "DL标签:transformer",
    "count": 0,
    "createdAt": "2026-07-02T00:00:00.000Z"
  },
  {
    "id": "dl-tag-086",
    "name": "encoder",
    "category": "DL",
    "description": "DL标签:encoder",
    "count": 0,
    "createdAt": "2026-07-02T00:00:00.000Z"
  },
  {
    "id": "dl-tag-087",
    "name": "decoder",
    "category": "DL",
    "description": "DL标签:decoder",
    "count": 0,
    "createdAt": "2026-07-02T00:00:00.000Z"
  },
  {
    "id": "dl-tag-088",
    "name": "multi-head",
    "category": "DL",
    "description": "DL标签:multi-head",
    "count": 0,
    "createdAt": "2026-07-02T00:00:00.000Z"
  },
  {
    "id": "dl-tag-089",
    "name": "attention",
    "category": "DL",
    "description": "DL标签:attention",
    "count": 0,
    "createdAt": "2026-07-02T00:00:00.000Z"
  },
  {
    "id": "dl-tag-090",
    "name": "layer",
    "category": "DL",
    "description": "DL标签:layer",
    "count": 0,
    "createdAt": "2026-07-02T00:00:00.000Z"
  },
  {
    "id": "dl-tag-091",
    "name": "norm",
    "category": "DL",
    "description": "DL标签:norm",
    "count": 0,
    "createdAt": "2026-07-02T00:00:00.000Z"
  },
  {
    "id": "dl-tag-092",
    "name": "residual",
    "category": "DL",
    "description": "DL标签:residual",
    "count": 0,
    "createdAt": "2026-07-02T00:00:00.000Z"
  },
  {
    "id": "dl-tag-093",
    "name": "connection",
    "category": "DL",
    "description": "DL标签:connection",
    "count": 0,
    "createdAt": "2026-07-02T00:00:00.000Z"
  },
  {
    "id": "dl-tag-094",
    "name": "skip",
    "category": "DL",
    "description": "DL标签:skip",
    "count": 0,
    "createdAt": "2026-07-02T00:00:00.000Z"
  },
  {
    "id": "dl-tag-095",
    "name": "connection",
    "category": "DL",
    "description": "DL标签:connection",
    "count": 0,
    "createdAt": "2026-07-02T00:00:00.000Z"
  },
  {
    "id": "dl-tag-096",
    "name": "gradient",
    "category": "DL",
    "description": "DL标签:gradient",
    "count": 0,
    "createdAt": "2026-07-02T00:00:00.000Z"
  },
  {
    "id": "dl-tag-097",
    "name": "vanishing",
    "category": "DL",
    "description": "DL标签:vanishing",
    "count": 0,
    "createdAt": "2026-07-02T00:00:00.000Z"
  },
  {
    "id": "dl-tag-098",
    "name": "gradient",
    "category": "DL",
    "description": "DL标签:gradient",
    "count": 0,
    "createdAt": "2026-07-02T00:00:00.000Z"
  },
  {
    "id": "dl-tag-099",
    "name": "exploding",
    "category": "DL",
    "description": "DL标签:exploding",
    "count": 0,
    "createdAt": "2026-07-02T00:00:00.000Z"
  },
  {
    "id": "dl-tag-100",
    "name": "weight",
    "category": "DL",
    "description": "DL标签:weight",
    "count": 0,
    "createdAt": "2026-07-02T00:00:00.000Z"
  },
  {
    "id": "dl-tag-101",
    "name": "decay",
    "category": "DL",
    "description": "DL标签:decay",
    "count": 0,
    "createdAt": "2026-07-02T00:00:00.000Z"
  },
  {
    "id": "dl-tag-102",
    "name": "learning",
    "category": "DL",
    "description": "DL标签:learning",
    "count": 0,
    "createdAt": "2026-07-02T00:00:00.000Z"
  },
  {
    "id": "dl-tag-103",
    "name": "rate",
    "category": "DL",
    "description": "DL标签:rate",
    "count": 0,
    "createdAt": "2026-07-02T00:00:00.000Z"
  },
  {
    "id": "dl-tag-104",
    "name": "scheduler",
    "category": "DL",
    "description": "DL标签:scheduler",
    "count": 0,
    "createdAt": "2026-07-02T00:00:00.000Z"
  },
  {
    "id": "dl-tag-105",
    "name": "warmup",
    "category": "DL",
    "description": "DL标签:warmup",
    "count": 0,
    "createdAt": "2026-07-02T00:00:00.000Z"
  },
  {
    "id": "dl-tag-106",
    "name": "early",
    "category": "DL",
    "description": "DL标签:early",
    "count": 0,
    "createdAt": "2026-07-02T00:00:00.000Z"
  },
  {
    "id": "dl-tag-107",
    "name": "stopping",
    "category": "DL",
    "description": "DL标签:stopping",
    "count": 0,
    "createdAt": "2026-07-02T00:00:00.000Z"
  },
  {
    "id": "dl-tag-108",
    "name": "fine-tuning",
    "category": "DL",
    "description": "DL标签:fine-tuning",
    "count": 0,
    "createdAt": "2026-07-02T00:00:00.000Z"
  },
  {
    "id": "dl-tag-109",
    "name": "transfer",
    "category": "DL",
    "description": "DL标签:transfer",
    "count": 0,
    "createdAt": "2026-07-02T00:00:00.000Z"
  },
  {
    "id": "dl-tag-110",
    "name": "learning",
    "category": "DL",
    "description": "DL标签:learning",
    "count": 0,
    "createdAt": "2026-07-02T00:00:00.000Z"
  },
  {
    "id": "dl-tag-111",
    "name": "pre-training",
    "category": "DL",
    "description": "DL标签:pre-training",
    "count": 0,
    "createdAt": "2026-07-02T00:00:00.000Z"
  },
  {
    "id": "dl-tag-112",
    "name": "DL标签112",
    "category": "DL",
    "description": "DL标签",
    "count": 0,
    "createdAt": "2026-07-02T00:00:00.000Z"
  },
  {
    "id": "dl-tag-113",
    "name": "DL标签113",
    "category": "DL",
    "description": "DL标签",
    "count": 0,
    "createdAt": "2026-07-02T00:00:00.000Z"
  },
  {
    "id": "dl-tag-114",
    "name": "DL标签114",
    "category": "DL",
    "description": "DL标签",
    "count": 0,
    "createdAt": "2026-07-02T00:00:00.000Z"
  },
  {
    "id": "dl-tag-115",
    "name": "DL标签115",
    "category": "DL",
    "description": "DL标签",
    "count": 0,
    "createdAt": "2026-07-02T00:00:00.000Z"
  },
  {
    "id": "dl-tag-116",
    "name": "DL标签116",
    "category": "DL",
    "description": "DL标签",
    "count": 0,
    "createdAt": "2026-07-02T00:00:00.000Z"
  },
  {
    "id": "dl-tag-117",
    "name": "DL标签117",
    "category": "DL",
    "description": "DL标签",
    "count": 0,
    "createdAt": "2026-07-02T00:00:00.000Z"
  },
  {
    "id": "dl-tag-118",
    "name": "DL标签118",
    "category": "DL",
    "description": "DL标签",
    "count": 0,
    "createdAt": "2026-07-02T00:00:00.000Z"
  },
  {
    "id": "dl-tag-119",
    "name": "DL标签119",
    "category": "DL",
    "description": "DL标签",
    "count": 0,
    "createdAt": "2026-07-02T00:00:00.000Z"
  },
  {
    "id": "dl-tag-120",
    "name": "DL标签120",
    "category": "DL",
    "description": "DL标签",
    "count": 0,
    "createdAt": "2026-07-02T00:00:00.000Z"
  },
  {
    "id": "dl-tag-121",
    "name": "DL标签121",
    "category": "DL",
    "description": "DL标签",
    "count": 0,
    "createdAt": "2026-07-02T00:00:00.000Z"
  },
  {
    "id": "dl-tag-122",
    "name": "DL标签122",
    "category": "DL",
    "description": "DL标签",
    "count": 0,
    "createdAt": "2026-07-02T00:00:00.000Z"
  },
  {
    "id": "dl-tag-123",
    "name": "DL标签123",
    "category": "DL",
    "description": "DL标签",
    "count": 0,
    "createdAt": "2026-07-02T00:00:00.000Z"
  },
  {
    "id": "dl-tag-124",
    "name": "DL标签124",
    "category": "DL",
    "description": "DL标签",
    "count": 0,
    "createdAt": "2026-07-02T00:00:00.000Z"
  },
  {
    "id": "dl-tag-125",
    "name": "DL标签125",
    "category": "DL",
    "description": "DL标签",
    "count": 0,
    "createdAt": "2026-07-02T00:00:00.000Z"
  },
  {
    "id": "dl-tag-126",
    "name": "DL标签126",
    "category": "DL",
    "description": "DL标签",
    "count": 0,
    "createdAt": "2026-07-02T00:00:00.000Z"
  },
  {
    "id": "dl-tag-127",
    "name": "DL标签127",
    "category": "DL",
    "description": "DL标签",
    "count": 0,
    "createdAt": "2026-07-02T00:00:00.000Z"
  },
  {
    "id": "dl-tag-128",
    "name": "DL标签128",
    "category": "DL",
    "description": "DL标签",
    "count": 0,
    "createdAt": "2026-07-02T00:00:00.000Z"
  },
  {
    "id": "dl-tag-129",
    "name": "DL标签129",
    "category": "DL",
    "description": "DL标签",
    "count": 0,
    "createdAt": "2026-07-02T00:00:00.000Z"
  },
  {
    "id": "dl-tag-130",
    "name": "DL标签130",
    "category": "DL",
    "description": "DL标签",
    "count": 0,
    "createdAt": "2026-07-02T00:00:00.000Z"
  },
  {
    "id": "dl-tag-131",
    "name": "DL标签131",
    "category": "DL",
    "description": "DL标签",
    "count": 0,
    "createdAt": "2026-07-02T00:00:00.000Z"
  },
  {
    "id": "dl-tag-132",
    "name": "DL标签132",
    "category": "DL",
    "description": "DL标签",
    "count": 0,
    "createdAt": "2026-07-02T00:00:00.000Z"
  },
  {
    "id": "dl-tag-133",
    "name": "DL标签133",
    "category": "DL",
    "description": "DL标签",
    "count": 0,
    "createdAt": "2026-07-02T00:00:00.000Z"
  },
  {
    "id": "dl-tag-134",
    "name": "DL标签134",
    "category": "DL",
    "description": "DL标签",
    "count": 0,
    "createdAt": "2026-07-02T00:00:00.000Z"
  },
  {
    "id": "dl-tag-135",
    "name": "DL标签135",
    "category": "DL",
    "description": "DL标签",
    "count": 0,
    "createdAt": "2026-07-02T00:00:00.000Z"
  },
  {
    "id": "dl-tag-136",
    "name": "DL标签136",
    "category": "DL",
    "description": "DL标签",
    "count": 0,
    "createdAt": "2026-07-02T00:00:00.000Z"
  },
  {
    "id": "dl-tag-137",
    "name": "DL标签137",
    "category": "DL",
    "description": "DL标签",
    "count": 0,
    "createdAt": "2026-07-02T00:00:00.000Z"
  },
  {
    "id": "dl-tag-138",
    "name": "DL标签138",
    "category": "DL",
    "description": "DL标签",
    "count": 0,
    "createdAt": "2026-07-02T00:00:00.000Z"
  },
  {
    "id": "dl-tag-139",
    "name": "DL标签139",
    "category": "DL",
    "description": "DL标签",
    "count": 0,
    "createdAt": "2026-07-02T00:00:00.000Z"
  },
  {
    "id": "dl-tag-140",
    "name": "DL标签140",
    "category": "DL",
    "description": "DL标签",
    "count": 0,
    "createdAt": "2026-07-02T00:00:00.000Z"
  },
  {
    "id": "dl-tag-141",
    "name": "DL标签141",
    "category": "DL",
    "description": "DL标签",
    "count": 0,
    "createdAt": "2026-07-02T00:00:00.000Z"
  },
  {
    "id": "dl-tag-142",
    "name": "DL标签142",
    "category": "DL",
    "description": "DL标签",
    "count": 0,
    "createdAt": "2026-07-02T00:00:00.000Z"
  },
  {
    "id": "dl-tag-143",
    "name": "DL标签143",
    "category": "DL",
    "description": "DL标签",
    "count": 0,
    "createdAt": "2026-07-02T00:00:00.000Z"
  },
  {
    "id": "dl-tag-144",
    "name": "DL标签144",
    "category": "DL",
    "description": "DL标签",
    "count": 0,
    "createdAt": "2026-07-02T00:00:00.000Z"
  },
  {
    "id": "dl-tag-145",
    "name": "DL标签145",
    "category": "DL",
    "description": "DL标签",
    "count": 0,
    "createdAt": "2026-07-02T00:00:00.000Z"
  },
  {
    "id": "dl-tag-146",
    "name": "DL标签146",
    "category": "DL",
    "description": "DL标签",
    "count": 0,
    "createdAt": "2026-07-02T00:00:00.000Z"
  },
  {
    "id": "dl-tag-147",
    "name": "DL标签147",
    "category": "DL",
    "description": "DL标签",
    "count": 0,
    "createdAt": "2026-07-02T00:00:00.000Z"
  },
  {
    "id": "dl-tag-148",
    "name": "DL标签148",
    "category": "DL",
    "description": "DL标签",
    "count": 0,
    "createdAt": "2026-07-02T00:00:00.000Z"
  },
  {
    "id": "dl-tag-149",
    "name": "DL标签149",
    "category": "DL",
    "description": "DL标签",
    "count": 0,
    "createdAt": "2026-07-02T00:00:00.000Z"
  },
  {
    "id": "dl-tag-150",
    "name": "DL标签150",
    "category": "DL",
    "description": "DL标签",
    "count": 0,
    "createdAt": "2026-07-02T00:00:00.000Z"
  },
  {
    "id": "dl-tag-151",
    "name": "DL标签151",
    "category": "DL",
    "description": "DL标签",
    "count": 0,
    "createdAt": "2026-07-02T00:00:00.000Z"
  },
  {
    "id": "dl-tag-152",
    "name": "DL标签152",
    "category": "DL",
    "description": "DL标签",
    "count": 0,
    "createdAt": "2026-07-02T00:00:00.000Z"
  },
  {
    "id": "dl-tag-153",
    "name": "DL标签153",
    "category": "DL",
    "description": "DL标签",
    "count": 0,
    "createdAt": "2026-07-02T00:00:00.000Z"
  },
  {
    "id": "dl-tag-154",
    "name": "DL标签154",
    "category": "DL",
    "description": "DL标签",
    "count": 0,
    "createdAt": "2026-07-02T00:00:00.000Z"
  },
  {
    "id": "dl-tag-155",
    "name": "DL标签155",
    "category": "DL",
    "description": "DL标签",
    "count": 0,
    "createdAt": "2026-07-02T00:00:00.000Z"
  },
  {
    "id": "dl-tag-156",
    "name": "DL标签156",
    "category": "DL",
    "description": "DL标签",
    "count": 0,
    "createdAt": "2026-07-02T00:00:00.000Z"
  },
  {
    "id": "dl-tag-157",
    "name": "DL标签157",
    "category": "DL",
    "description": "DL标签",
    "count": 0,
    "createdAt": "2026-07-02T00:00:00.000Z"
  },
  {
    "id": "dl-tag-158",
    "name": "DL标签158",
    "category": "DL",
    "description": "DL标签",
    "count": 0,
    "createdAt": "2026-07-02T00:00:00.000Z"
  },
  {
    "id": "dl-tag-159",
    "name": "DL标签159",
    "category": "DL",
    "description": "DL标签",
    "count": 0,
    "createdAt": "2026-07-02T00:00:00.000Z"
  },
  {
    "id": "dl-tag-160",
    "name": "DL标签160",
    "category": "DL",
    "description": "DL标签",
    "count": 0,
    "createdAt": "2026-07-02T00:00:00.000Z"
  },
  {
    "id": "dl-tag-161",
    "name": "DL标签161",
    "category": "DL",
    "description": "DL标签",
    "count": 0,
    "createdAt": "2026-07-02T00:00:00.000Z"
  },
  {
    "id": "dl-tag-162",
    "name": "DL标签162",
    "category": "DL",
    "description": "DL标签",
    "count": 0,
    "createdAt": "2026-07-02T00:00:00.000Z"
  },
  {
    "id": "dl-tag-163",
    "name": "DL标签163",
    "category": "DL",
    "description": "DL标签",
    "count": 0,
    "createdAt": "2026-07-02T00:00:00.000Z"
  },
  {
    "id": "dl-tag-164",
    "name": "DL标签164",
    "category": "DL",
    "description": "DL标签",
    "count": 0,
    "createdAt": "2026-07-02T00:00:00.000Z"
  },
  {
    "id": "dl-tag-165",
    "name": "DL标签165",
    "category": "DL",
    "description": "DL标签",
    "count": 0,
    "createdAt": "2026-07-02T00:00:00.000Z"
  },
  {
    "id": "dl-tag-166",
    "name": "DL标签166",
    "category": "DL",
    "description": "DL标签",
    "count": 0,
    "createdAt": "2026-07-02T00:00:00.000Z"
  },
  {
    "id": "dl-tag-167",
    "name": "DL标签167",
    "category": "DL",
    "description": "DL标签",
    "count": 0,
    "createdAt": "2026-07-02T00:00:00.000Z"
  },
  {
    "id": "dl-tag-168",
    "name": "DL标签168",
    "category": "DL",
    "description": "DL标签",
    "count": 0,
    "createdAt": "2026-07-02T00:00:00.000Z"
  },
  {
    "id": "dl-tag-169",
    "name": "DL标签169",
    "category": "DL",
    "description": "DL标签",
    "count": 0,
    "createdAt": "2026-07-02T00:00:00.000Z"
  },
  {
    "id": "dl-tag-170",
    "name": "DL标签170",
    "category": "DL",
    "description": "DL标签",
    "count": 0,
    "createdAt": "2026-07-02T00:00:00.000Z"
  },
  {
    "id": "dl-tag-171",
    "name": "DL标签171",
    "category": "DL",
    "description": "DL标签",
    "count": 0,
    "createdAt": "2026-07-02T00:00:00.000Z"
  },
  {
    "id": "dl-tag-172",
    "name": "DL标签172",
    "category": "DL",
    "description": "DL标签",
    "count": 0,
    "createdAt": "2026-07-02T00:00:00.000Z"
  },
  {
    "id": "dl-tag-173",
    "name": "DL标签173",
    "category": "DL",
    "description": "DL标签",
    "count": 0,
    "createdAt": "2026-07-02T00:00:00.000Z"
  },
  {
    "id": "dl-tag-174",
    "name": "DL标签174",
    "category": "DL",
    "description": "DL标签",
    "count": 0,
    "createdAt": "2026-07-02T00:00:00.000Z"
  },
  {
    "id": "dl-tag-175",
    "name": "DL标签175",
    "category": "DL",
    "description": "DL标签",
    "count": 0,
    "createdAt": "2026-07-02T00:00:00.000Z"
  },
  {
    "id": "dl-tag-176",
    "name": "DL标签176",
    "category": "DL",
    "description": "DL标签",
    "count": 0,
    "createdAt": "2026-07-02T00:00:00.000Z"
  },
  {
    "id": "dl-tag-177",
    "name": "DL标签177",
    "category": "DL",
    "description": "DL标签",
    "count": 0,
    "createdAt": "2026-07-02T00:00:00.000Z"
  },
  {
    "id": "dl-tag-178",
    "name": "DL标签178",
    "category": "DL",
    "description": "DL标签",
    "count": 0,
    "createdAt": "2026-07-02T00:00:00.000Z"
  },
  {
    "id": "dl-tag-179",
    "name": "DL标签179",
    "category": "DL",
    "description": "DL标签",
    "count": 0,
    "createdAt": "2026-07-02T00:00:00.000Z"
  },
  {
    "id": "dl-tag-180",
    "name": "DL标签180",
    "category": "DL",
    "description": "DL标签",
    "count": 0,
    "createdAt": "2026-07-02T00:00:00.000Z"
  },
  {
    "id": "dl-tag-181",
    "name": "DL标签181",
    "category": "DL",
    "description": "DL标签",
    "count": 0,
    "createdAt": "2026-07-02T00:00:00.000Z"
  },
  {
    "id": "dl-tag-182",
    "name": "DL标签182",
    "category": "DL",
    "description": "DL标签",
    "count": 0,
    "createdAt": "2026-07-02T00:00:00.000Z"
  },
  {
    "id": "dl-tag-183",
    "name": "DL标签183",
    "category": "DL",
    "description": "DL标签",
    "count": 0,
    "createdAt": "2026-07-02T00:00:00.000Z"
  },
  {
    "id": "dl-tag-184",
    "name": "DL标签184",
    "category": "DL",
    "description": "DL标签",
    "count": 0,
    "createdAt": "2026-07-02T00:00:00.000Z"
  },
  {
    "id": "dl-tag-185",
    "name": "DL标签185",
    "category": "DL",
    "description": "DL标签",
    "count": 0,
    "createdAt": "2026-07-02T00:00:00.000Z"
  },
  {
    "id": "dl-tag-186",
    "name": "DL标签186",
    "category": "DL",
    "description": "DL标签",
    "count": 0,
    "createdAt": "2026-07-02T00:00:00.000Z"
  },
  {
    "id": "dl-tag-187",
    "name": "DL标签187",
    "category": "DL",
    "description": "DL标签",
    "count": 0,
    "createdAt": "2026-07-02T00:00:00.000Z"
  },
  {
    "id": "dl-tag-188",
    "name": "DL标签188",
    "category": "DL",
    "description": "DL标签",
    "count": 0,
    "createdAt": "2026-07-02T00:00:00.000Z"
  },
  {
    "id": "dl-tag-189",
    "name": "DL标签189",
    "category": "DL",
    "description": "DL标签",
    "count": 0,
    "createdAt": "2026-07-02T00:00:00.000Z"
  },
  {
    "id": "dl-tag-190",
    "name": "DL标签190",
    "category": "DL",
    "description": "DL标签",
    "count": 0,
    "createdAt": "2026-07-02T00:00:00.000Z"
  },
  {
    "id": "dl-tag-191",
    "name": "DL标签191",
    "category": "DL",
    "description": "DL标签",
    "count": 0,
    "createdAt": "2026-07-02T00:00:00.000Z"
  },
  {
    "id": "dl-tag-192",
    "name": "DL标签192",
    "category": "DL",
    "description": "DL标签",
    "count": 0,
    "createdAt": "2026-07-02T00:00:00.000Z"
  },
  {
    "id": "dl-tag-193",
    "name": "DL标签193",
    "category": "DL",
    "description": "DL标签",
    "count": 0,
    "createdAt": "2026-07-02T00:00:00.000Z"
  },
  {
    "id": "dl-tag-194",
    "name": "DL标签194",
    "category": "DL",
    "description": "DL标签",
    "count": 0,
    "createdAt": "2026-07-02T00:00:00.000Z"
  },
  {
    "id": "dl-tag-195",
    "name": "DL标签195",
    "category": "DL",
    "description": "DL标签",
    "count": 0,
    "createdAt": "2026-07-02T00:00:00.000Z"
  },
  {
    "id": "dl-tag-196",
    "name": "DL标签196",
    "category": "DL",
    "description": "DL标签",
    "count": 0,
    "createdAt": "2026-07-02T00:00:00.000Z"
  },
  {
    "id": "dl-tag-197",
    "name": "DL标签197",
    "category": "DL",
    "description": "DL标签",
    "count": 0,
    "createdAt": "2026-07-02T00:00:00.000Z"
  },
  {
    "id": "dl-tag-198",
    "name": "DL标签198",
    "category": "DL",
    "description": "DL标签",
    "count": 0,
    "createdAt": "2026-07-02T00:00:00.000Z"
  },
  {
    "id": "dl-tag-199",
    "name": "DL标签199",
    "category": "DL",
    "description": "DL标签",
    "count": 0,
    "createdAt": "2026-07-02T00:00:00.000Z"
  },
  {
    "id": "dl-tag-200",
    "name": "DL标签200",
    "category": "DL",
    "description": "DL标签",
    "count": 0,
    "createdAt": "2026-07-02T00:00:00.000Z"
  },
  {
    "id": "dl-tag-201",
    "name": "DL标签201",
    "category": "DL",
    "description": "DL标签",
    "count": 0,
    "createdAt": "2026-07-02T00:00:00.000Z"
  },
  {
    "id": "dl-tag-202",
    "name": "DL标签202",
    "category": "DL",
    "description": "DL标签",
    "count": 0,
    "createdAt": "2026-07-02T00:00:00.000Z"
  },
  {
    "id": "dl-tag-203",
    "name": "DL标签203",
    "category": "DL",
    "description": "DL标签",
    "count": 0,
    "createdAt": "2026-07-02T00:00:00.000Z"
  },
  {
    "id": "dl-tag-204",
    "name": "DL标签204",
    "category": "DL",
    "description": "DL标签",
    "count": 0,
    "createdAt": "2026-07-02T00:00:00.000Z"
  },
  {
    "id": "dl-tag-205",
    "name": "DL标签205",
    "category": "DL",
    "description": "DL标签",
    "count": 0,
    "createdAt": "2026-07-02T00:00:00.000Z"
  },
  {
    "id": "dl-tag-206",
    "name": "DL标签206",
    "category": "DL",
    "description": "DL标签",
    "count": 0,
    "createdAt": "2026-07-02T00:00:00.000Z"
  },
  {
    "id": "dl-tag-207",
    "name": "DL标签207",
    "category": "DL",
    "description": "DL标签",
    "count": 0,
    "createdAt": "2026-07-02T00:00:00.000Z"
  },
  {
    "id": "dl-tag-208",
    "name": "DL标签208",
    "category": "DL",
    "description": "DL标签",
    "count": 0,
    "createdAt": "2026-07-02T00:00:00.000Z"
  },
  {
    "id": "dl-tag-209",
    "name": "DL标签209",
    "category": "DL",
    "description": "DL标签",
    "count": 0,
    "createdAt": "2026-07-02T00:00:00.000Z"
  },
  {
    "id": "dl-tag-210",
    "name": "DL标签210",
    "category": "DL",
    "description": "DL标签",
    "count": 0,
    "createdAt": "2026-07-02T00:00:00.000Z"
  },
  {
    "id": "dl-tag-211",
    "name": "DL标签211",
    "category": "DL",
    "description": "DL标签",
    "count": 0,
    "createdAt": "2026-07-02T00:00:00.000Z"
  },
  {
    "id": "dl-tag-212",
    "name": "DL标签212",
    "category": "DL",
    "description": "DL标签",
    "count": 0,
    "createdAt": "2026-07-02T00:00:00.000Z"
  },
  {
    "id": "dl-tag-213",
    "name": "DL标签213",
    "category": "DL",
    "description": "DL标签",
    "count": 0,
    "createdAt": "2026-07-02T00:00:00.000Z"
  },
  {
    "id": "dl-tag-214",
    "name": "DL标签214",
    "category": "DL",
    "description": "DL标签",
    "count": 0,
    "createdAt": "2026-07-02T00:00:00.000Z"
  },
  {
    "id": "dl-tag-215",
    "name": "DL标签215",
    "category": "DL",
    "description": "DL标签",
    "count": 0,
    "createdAt": "2026-07-02T00:00:00.000Z"
  },
  {
    "id": "dl-tag-216",
    "name": "DL标签216",
    "category": "DL",
    "description": "DL标签",
    "count": 0,
    "createdAt": "2026-07-02T00:00:00.000Z"
  },
  {
    "id": "dl-tag-217",
    "name": "DL标签217",
    "category": "DL",
    "description": "DL标签",
    "count": 0,
    "createdAt": "2026-07-02T00:00:00.000Z"
  },
  {
    "id": "dl-tag-218",
    "name": "DL标签218",
    "category": "DL",
    "description": "DL标签",
    "count": 0,
    "createdAt": "2026-07-02T00:00:00.000Z"
  },
  {
    "id": "dl-tag-219",
    "name": "DL标签219",
    "category": "DL",
    "description": "DL标签",
    "count": 0,
    "createdAt": "2026-07-02T00:00:00.000Z"
  },
  {
    "id": "dl-tag-220",
    "name": "DL标签220",
    "category": "DL",
    "description": "DL标签",
    "count": 0,
    "createdAt": "2026-07-02T00:00:00.000Z"
  },
  {
    "id": "dl-tag-221",
    "name": "DL标签221",
    "category": "DL",
    "description": "DL标签",
    "count": 0,
    "createdAt": "2026-07-02T00:00:00.000Z"
  },
  {
    "id": "dl-tag-222",
    "name": "DL标签222",
    "category": "DL",
    "description": "DL标签",
    "count": 0,
    "createdAt": "2026-07-02T00:00:00.000Z"
  },
  {
    "id": "dl-tag-223",
    "name": "DL标签223",
    "category": "DL",
    "description": "DL标签",
    "count": 0,
    "createdAt": "2026-07-02T00:00:00.000Z"
  },
  {
    "id": "dl-tag-224",
    "name": "DL标签224",
    "category": "DL",
    "description": "DL标签",
    "count": 0,
    "createdAt": "2026-07-02T00:00:00.000Z"
  },
  {
    "id": "dl-tag-225",
    "name": "DL标签225",
    "category": "DL",
    "description": "DL标签",
    "count": 0,
    "createdAt": "2026-07-02T00:00:00.000Z"
  },
  {
    "id": "dl-tag-226",
    "name": "DL标签226",
    "category": "DL",
    "description": "DL标签",
    "count": 0,
    "createdAt": "2026-07-02T00:00:00.000Z"
  },
  {
    "id": "dl-tag-227",
    "name": "DL标签227",
    "category": "DL",
    "description": "DL标签",
    "count": 0,
    "createdAt": "2026-07-02T00:00:00.000Z"
  },
  {
    "id": "dl-tag-228",
    "name": "DL标签228",
    "category": "DL",
    "description": "DL标签",
    "count": 0,
    "createdAt": "2026-07-02T00:00:00.000Z"
  },
  {
    "id": "dl-tag-229",
    "name": "DL标签229",
    "category": "DL",
    "description": "DL标签",
    "count": 0,
    "createdAt": "2026-07-02T00:00:00.000Z"
  },
  {
    "id": "dl-tag-230",
    "name": "DL标签230",
    "category": "DL",
    "description": "DL标签",
    "count": 0,
    "createdAt": "2026-07-02T00:00:00.000Z"
  },
  {
    "id": "dl-tag-231",
    "name": "DL标签231",
    "category": "DL",
    "description": "DL标签",
    "count": 0,
    "createdAt": "2026-07-02T00:00:00.000Z"
  },
  {
    "id": "dl-tag-232",
    "name": "DL标签232",
    "category": "DL",
    "description": "DL标签",
    "count": 0,
    "createdAt": "2026-07-02T00:00:00.000Z"
  },
  {
    "id": "dl-tag-233",
    "name": "DL标签233",
    "category": "DL",
    "description": "DL标签",
    "count": 0,
    "createdAt": "2026-07-02T00:00:00.000Z"
  },
  {
    "id": "dl-tag-234",
    "name": "DL标签234",
    "category": "DL",
    "description": "DL标签",
    "count": 0,
    "createdAt": "2026-07-02T00:00:00.000Z"
  },
  {
    "id": "dl-tag-235",
    "name": "DL标签235",
    "category": "DL",
    "description": "DL标签",
    "count": 0,
    "createdAt": "2026-07-02T00:00:00.000Z"
  },
  {
    "id": "dl-tag-236",
    "name": "DL标签236",
    "category": "DL",
    "description": "DL标签",
    "count": 0,
    "createdAt": "2026-07-02T00:00:00.000Z"
  },
  {
    "id": "dl-tag-237",
    "name": "DL标签237",
    "category": "DL",
    "description": "DL标签",
    "count": 0,
    "createdAt": "2026-07-02T00:00:00.000Z"
  },
  {
    "id": "dl-tag-238",
    "name": "DL标签238",
    "category": "DL",
    "description": "DL标签",
    "count": 0,
    "createdAt": "2026-07-02T00:00:00.000Z"
  },
  {
    "id": "dl-tag-239",
    "name": "DL标签239",
    "category": "DL",
    "description": "DL标签",
    "count": 0,
    "createdAt": "2026-07-02T00:00:00.000Z"
  },
  {
    "id": "dl-tag-240",
    "name": "DL标签240",
    "category": "DL",
    "description": "DL标签",
    "count": 0,
    "createdAt": "2026-07-02T00:00:00.000Z"
  },
  {
    "id": "dl-tag-241",
    "name": "DL标签241",
    "category": "DL",
    "description": "DL标签",
    "count": 0,
    "createdAt": "2026-07-02T00:00:00.000Z"
  },
  {
    "id": "dl-tag-242",
    "name": "DL标签242",
    "category": "DL",
    "description": "DL标签",
    "count": 0,
    "createdAt": "2026-07-02T00:00:00.000Z"
  },
  {
    "id": "dl-tag-243",
    "name": "DL标签243",
    "category": "DL",
    "description": "DL标签",
    "count": 0,
    "createdAt": "2026-07-02T00:00:00.000Z"
  },
  {
    "id": "dl-tag-244",
    "name": "DL标签244",
    "category": "DL",
    "description": "DL标签",
    "count": 0,
    "createdAt": "2026-07-02T00:00:00.000Z"
  },
  {
    "id": "dl-tag-245",
    "name": "DL标签245",
    "category": "DL",
    "description": "DL标签",
    "count": 0,
    "createdAt": "2026-07-02T00:00:00.000Z"
  },
  {
    "id": "dl-tag-246",
    "name": "DL标签246",
    "category": "DL",
    "description": "DL标签",
    "count": 0,
    "createdAt": "2026-07-02T00:00:00.000Z"
  },
  {
    "id": "dl-tag-247",
    "name": "DL标签247",
    "category": "DL",
    "description": "DL标签",
    "count": 0,
    "createdAt": "2026-07-02T00:00:00.000Z"
  },
  {
    "id": "dl-tag-248",
    "name": "DL标签248",
    "category": "DL",
    "description": "DL标签",
    "count": 0,
    "createdAt": "2026-07-02T00:00:00.000Z"
  },
  {
    "id": "dl-tag-249",
    "name": "DL标签249",
    "category": "DL",
    "description": "DL标签",
    "count": 0,
    "createdAt": "2026-07-02T00:00:00.000Z"
  },
  {
    "id": "dl-tag-250",
    "name": "DL标签250",
    "category": "DL",
    "description": "DL标签",
    "count": 0,
    "createdAt": "2026-07-02T00:00:00.000Z"
  },
  {
    "id": "dl-tag-251",
    "name": "DL标签251",
    "category": "DL",
    "description": "DL标签",
    "count": 0,
    "createdAt": "2026-07-02T00:00:00.000Z"
  },
  {
    "id": "dl-tag-252",
    "name": "DL标签252",
    "category": "DL",
    "description": "DL标签",
    "count": 0,
    "createdAt": "2026-07-02T00:00:00.000Z"
  },
  {
    "id": "dl-tag-253",
    "name": "DL标签253",
    "category": "DL",
    "description": "DL标签",
    "count": 0,
    "createdAt": "2026-07-02T00:00:00.000Z"
  },
  {
    "id": "dl-tag-254",
    "name": "DL标签254",
    "category": "DL",
    "description": "DL标签",
    "count": 0,
    "createdAt": "2026-07-02T00:00:00.000Z"
  },
  {
    "id": "dl-tag-255",
    "name": "DL标签255",
    "category": "DL",
    "description": "DL标签",
    "count": 0,
    "createdAt": "2026-07-02T00:00:00.000Z"
  },
  {
    "id": "dl-tag-256",
    "name": "DL标签256",
    "category": "DL",
    "description": "DL标签",
    "count": 0,
    "createdAt": "2026-07-02T00:00:00.000Z"
  },
  {
    "id": "dl-tag-257",
    "name": "DL标签257",
    "category": "DL",
    "description": "DL标签",
    "count": 0,
    "createdAt": "2026-07-02T00:00:00.000Z"
  },
  {
    "id": "dl-tag-258",
    "name": "DL标签258",
    "category": "DL",
    "description": "DL标签",
    "count": 0,
    "createdAt": "2026-07-02T00:00:00.000Z"
  },
  {
    "id": "dl-tag-259",
    "name": "DL标签259",
    "category": "DL",
    "description": "DL标签",
    "count": 0,
    "createdAt": "2026-07-02T00:00:00.000Z"
  },
  {
    "id": "dl-tag-260",
    "name": "DL标签260",
    "category": "DL",
    "description": "DL标签",
    "count": 0,
    "createdAt": "2026-07-02T00:00:00.000Z"
  },
  {
    "id": "dl-tag-261",
    "name": "DL标签261",
    "category": "DL",
    "description": "DL标签",
    "count": 0,
    "createdAt": "2026-07-02T00:00:00.000Z"
  },
  {
    "id": "dl-tag-262",
    "name": "DL标签262",
    "category": "DL",
    "description": "DL标签",
    "count": 0,
    "createdAt": "2026-07-02T00:00:00.000Z"
  },
  {
    "id": "dl-tag-263",
    "name": "DL标签263",
    "category": "DL",
    "description": "DL标签",
    "count": 0,
    "createdAt": "2026-07-02T00:00:00.000Z"
  },
  {
    "id": "dl-tag-264",
    "name": "DL标签264",
    "category": "DL",
    "description": "DL标签",
    "count": 0,
    "createdAt": "2026-07-02T00:00:00.000Z"
  },
  {
    "id": "dl-tag-265",
    "name": "DL标签265",
    "category": "DL",
    "description": "DL标签",
    "count": 0,
    "createdAt": "2026-07-02T00:00:00.000Z"
  },
  {
    "id": "dl-tag-266",
    "name": "DL标签266",
    "category": "DL",
    "description": "DL标签",
    "count": 0,
    "createdAt": "2026-07-02T00:00:00.000Z"
  },
  {
    "id": "dl-tag-267",
    "name": "DL标签267",
    "category": "DL",
    "description": "DL标签",
    "count": 0,
    "createdAt": "2026-07-02T00:00:00.000Z"
  },
  {
    "id": "dl-tag-268",
    "name": "DL标签268",
    "category": "DL",
    "description": "DL标签",
    "count": 0,
    "createdAt": "2026-07-02T00:00:00.000Z"
  },
  {
    "id": "dl-tag-269",
    "name": "DL标签269",
    "category": "DL",
    "description": "DL标签",
    "count": 0,
    "createdAt": "2026-07-02T00:00:00.000Z"
  },
  {
    "id": "dl-tag-270",
    "name": "DL标签270",
    "category": "DL",
    "description": "DL标签",
    "count": 0,
    "createdAt": "2026-07-02T00:00:00.000Z"
  },
  {
    "id": "dl-tag-271",
    "name": "DL标签271",
    "category": "DL",
    "description": "DL标签",
    "count": 0,
    "createdAt": "2026-07-02T00:00:00.000Z"
  },
  {
    "id": "dl-tag-272",
    "name": "DL标签272",
    "category": "DL",
    "description": "DL标签",
    "count": 0,
    "createdAt": "2026-07-02T00:00:00.000Z"
  },
  {
    "id": "dl-tag-273",
    "name": "DL标签273",
    "category": "DL",
    "description": "DL标签",
    "count": 0,
    "createdAt": "2026-07-02T00:00:00.000Z"
  },
  {
    "id": "dl-tag-274",
    "name": "DL标签274",
    "category": "DL",
    "description": "DL标签",
    "count": 0,
    "createdAt": "2026-07-02T00:00:00.000Z"
  },
  {
    "id": "dl-tag-275",
    "name": "DL标签275",
    "category": "DL",
    "description": "DL标签",
    "count": 0,
    "createdAt": "2026-07-02T00:00:00.000Z"
  },
  {
    "id": "dl-tag-276",
    "name": "DL标签276",
    "category": "DL",
    "description": "DL标签",
    "count": 0,
    "createdAt": "2026-07-02T00:00:00.000Z"
  },
  {
    "id": "dl-tag-277",
    "name": "DL标签277",
    "category": "DL",
    "description": "DL标签",
    "count": 0,
    "createdAt": "2026-07-02T00:00:00.000Z"
  },
  {
    "id": "dl-tag-278",
    "name": "DL标签278",
    "category": "DL",
    "description": "DL标签",
    "count": 0,
    "createdAt": "2026-07-02T00:00:00.000Z"
  },
  {
    "id": "dl-tag-279",
    "name": "DL标签279",
    "category": "DL",
    "description": "DL标签",
    "count": 0,
    "createdAt": "2026-07-02T00:00:00.000Z"
  },
  {
    "id": "dl-tag-280",
    "name": "DL标签280",
    "category": "DL",
    "description": "DL标签",
    "count": 0,
    "createdAt": "2026-07-02T00:00:00.000Z"
  },
  {
    "id": "dl-tag-281",
    "name": "DL标签281",
    "category": "DL",
    "description": "DL标签",
    "count": 0,
    "createdAt": "2026-07-02T00:00:00.000Z"
  },
  {
    "id": "dl-tag-282",
    "name": "DL标签282",
    "category": "DL",
    "description": "DL标签",
    "count": 0,
    "createdAt": "2026-07-02T00:00:00.000Z"
  },
  {
    "id": "dl-tag-283",
    "name": "DL标签283",
    "category": "DL",
    "description": "DL标签",
    "count": 0,
    "createdAt": "2026-07-02T00:00:00.000Z"
  },
  {
    "id": "dl-tag-284",
    "name": "DL标签284",
    "category": "DL",
    "description": "DL标签",
    "count": 0,
    "createdAt": "2026-07-02T00:00:00.000Z"
  },
  {
    "id": "dl-tag-285",
    "name": "DL标签285",
    "category": "DL",
    "description": "DL标签",
    "count": 0,
    "createdAt": "2026-07-02T00:00:00.000Z"
  },
  {
    "id": "dl-tag-286",
    "name": "DL标签286",
    "category": "DL",
    "description": "DL标签",
    "count": 0,
    "createdAt": "2026-07-02T00:00:00.000Z"
  },
  {
    "id": "dl-tag-287",
    "name": "DL标签287",
    "category": "DL",
    "description": "DL标签",
    "count": 0,
    "createdAt": "2026-07-02T00:00:00.000Z"
  },
  {
    "id": "dl-tag-288",
    "name": "DL标签288",
    "category": "DL",
    "description": "DL标签",
    "count": 0,
    "createdAt": "2026-07-02T00:00:00.000Z"
  },
  {
    "id": "dl-tag-289",
    "name": "DL标签289",
    "category": "DL",
    "description": "DL标签",
    "count": 0,
    "createdAt": "2026-07-02T00:00:00.000Z"
  },
  {
    "id": "dl-tag-290",
    "name": "DL标签290",
    "category": "DL",
    "description": "DL标签",
    "count": 0,
    "createdAt": "2026-07-02T00:00:00.000Z"
  },
  {
    "id": "dl-tag-291",
    "name": "DL标签291",
    "category": "DL",
    "description": "DL标签",
    "count": 0,
    "createdAt": "2026-07-02T00:00:00.000Z"
  },
  {
    "id": "dl-tag-292",
    "name": "DL标签292",
    "category": "DL",
    "description": "DL标签",
    "count": 0,
    "createdAt": "2026-07-02T00:00:00.000Z"
  },
  {
    "id": "dl-tag-293",
    "name": "DL标签293",
    "category": "DL",
    "description": "DL标签",
    "count": 0,
    "createdAt": "2026-07-02T00:00:00.000Z"
  },
  {
    "id": "dl-tag-294",
    "name": "DL标签294",
    "category": "DL",
    "description": "DL标签",
    "count": 0,
    "createdAt": "2026-07-02T00:00:00.000Z"
  },
  {
    "id": "dl-tag-295",
    "name": "DL标签295",
    "category": "DL",
    "description": "DL标签",
    "count": 0,
    "createdAt": "2026-07-02T00:00:00.000Z"
  },
  {
    "id": "dl-tag-296",
    "name": "DL标签296",
    "category": "DL",
    "description": "DL标签",
    "count": 0,
    "createdAt": "2026-07-02T00:00:00.000Z"
  },
  {
    "id": "dl-tag-297",
    "name": "DL标签297",
    "category": "DL",
    "description": "DL标签",
    "count": 0,
    "createdAt": "2026-07-02T00:00:00.000Z"
  },
  {
    "id": "dl-tag-298",
    "name": "DL标签298",
    "category": "DL",
    "description": "DL标签",
    "count": 0,
    "createdAt": "2026-07-02T00:00:00.000Z"
  },
  {
    "id": "dl-tag-299",
    "name": "DL标签299",
    "category": "DL",
    "description": "DL标签",
    "count": 0,
    "createdAt": "2026-07-02T00:00:00.000Z"
  },
  {
    "id": "dl-tag-300",
    "name": "DL标签300",
    "category": "DL",
    "description": "DL标签",
    "count": 0,
    "createdAt": "2026-07-02T00:00:00.000Z"
  },
  {
    "id": "dl-tag-301",
    "name": "DL标签301",
    "category": "DL",
    "description": "DL标签",
    "count": 0,
    "createdAt": "2026-07-02T00:00:00.000Z"
  },
  {
    "id": "dl-tag-302",
    "name": "DL标签302",
    "category": "DL",
    "description": "DL标签",
    "count": 0,
    "createdAt": "2026-07-02T00:00:00.000Z"
  },
  {
    "id": "dl-tag-303",
    "name": "DL标签303",
    "category": "DL",
    "description": "DL标签",
    "count": 0,
    "createdAt": "2026-07-02T00:00:00.000Z"
  },
  {
    "id": "dl-tag-304",
    "name": "DL标签304",
    "category": "DL",
    "description": "DL标签",
    "count": 0,
    "createdAt": "2026-07-02T00:00:00.000Z"
  },
  {
    "id": "dl-tag-305",
    "name": "DL标签305",
    "category": "DL",
    "description": "DL标签",
    "count": 0,
    "createdAt": "2026-07-02T00:00:00.000Z"
  },
  {
    "id": "dl-tag-306",
    "name": "DL标签306",
    "category": "DL",
    "description": "DL标签",
    "count": 0,
    "createdAt": "2026-07-02T00:00:00.000Z"
  },
  {
    "id": "dl-tag-307",
    "name": "DL标签307",
    "category": "DL",
    "description": "DL标签",
    "count": 0,
    "createdAt": "2026-07-02T00:00:00.000Z"
  },
  {
    "id": "dl-tag-308",
    "name": "DL标签308",
    "category": "DL",
    "description": "DL标签",
    "count": 0,
    "createdAt": "2026-07-02T00:00:00.000Z"
  },
  {
    "id": "dl-tag-309",
    "name": "DL标签309",
    "category": "DL",
    "description": "DL标签",
    "count": 0,
    "createdAt": "2026-07-02T00:00:00.000Z"
  },
  {
    "id": "dl-tag-310",
    "name": "DL标签310",
    "category": "DL",
    "description": "DL标签",
    "count": 0,
    "createdAt": "2026-07-02T00:00:00.000Z"
  },
  {
    "id": "dl-tag-311",
    "name": "DL标签311",
    "category": "DL",
    "description": "DL标签",
    "count": 0,
    "createdAt": "2026-07-02T00:00:00.000Z"
  },
  {
    "id": "dl-tag-312",
    "name": "DL标签312",
    "category": "DL",
    "description": "DL标签",
    "count": 0,
    "createdAt": "2026-07-02T00:00:00.000Z"
  },
  {
    "id": "dl-tag-313",
    "name": "DL标签313",
    "category": "DL",
    "description": "DL标签",
    "count": 0,
    "createdAt": "2026-07-02T00:00:00.000Z"
  },
  {
    "id": "dl-tag-314",
    "name": "DL标签314",
    "category": "DL",
    "description": "DL标签",
    "count": 0,
    "createdAt": "2026-07-02T00:00:00.000Z"
  },
  {
    "id": "dl-tag-315",
    "name": "DL标签315",
    "category": "DL",
    "description": "DL标签",
    "count": 0,
    "createdAt": "2026-07-02T00:00:00.000Z"
  },
  {
    "id": "dl-tag-316",
    "name": "DL标签316",
    "category": "DL",
    "description": "DL标签",
    "count": 0,
    "createdAt": "2026-07-02T00:00:00.000Z"
  },
  {
    "id": "dl-tag-317",
    "name": "DL标签317",
    "category": "DL",
    "description": "DL标签",
    "count": 0,
    "createdAt": "2026-07-02T00:00:00.000Z"
  },
  {
    "id": "dl-tag-318",
    "name": "DL标签318",
    "category": "DL",
    "description": "DL标签",
    "count": 0,
    "createdAt": "2026-07-02T00:00:00.000Z"
  },
  {
    "id": "dl-tag-319",
    "name": "DL标签319",
    "category": "DL",
    "description": "DL标签",
    "count": 0,
    "createdAt": "2026-07-02T00:00:00.000Z"
  },
  {
    "id": "dl-tag-320",
    "name": "DL标签320",
    "category": "DL",
    "description": "DL标签",
    "count": 0,
    "createdAt": "2026-07-02T00:00:00.000Z"
  },
  {
    "id": "dl-tag-321",
    "name": "DL标签321",
    "category": "DL",
    "description": "DL标签",
    "count": 0,
    "createdAt": "2026-07-02T00:00:00.000Z"
  },
  {
    "id": "dl-tag-322",
    "name": "DL标签322",
    "category": "DL",
    "description": "DL标签",
    "count": 0,
    "createdAt": "2026-07-02T00:00:00.000Z"
  },
  {
    "id": "dl-tag-323",
    "name": "DL标签323",
    "category": "DL",
    "description": "DL标签",
    "count": 0,
    "createdAt": "2026-07-02T00:00:00.000Z"
  },
  {
    "id": "dl-tag-324",
    "name": "DL标签324",
    "category": "DL",
    "description": "DL标签",
    "count": 0,
    "createdAt": "2026-07-02T00:00:00.000Z"
  },
  {
    "id": "dl-tag-325",
    "name": "DL标签325",
    "category": "DL",
    "description": "DL标签",
    "count": 0,
    "createdAt": "2026-07-02T00:00:00.000Z"
  },
  {
    "id": "dl-tag-326",
    "name": "DL标签326",
    "category": "DL",
    "description": "DL标签",
    "count": 0,
    "createdAt": "2026-07-02T00:00:00.000Z"
  },
  {
    "id": "dl-tag-327",
    "name": "DL标签327",
    "category": "DL",
    "description": "DL标签",
    "count": 0,
    "createdAt": "2026-07-02T00:00:00.000Z"
  },
  {
    "id": "dl-tag-328",
    "name": "DL标签328",
    "category": "DL",
    "description": "DL标签",
    "count": 0,
    "createdAt": "2026-07-02T00:00:00.000Z"
  },
  {
    "id": "dl-tag-329",
    "name": "DL标签329",
    "category": "DL",
    "description": "DL标签",
    "count": 0,
    "createdAt": "2026-07-02T00:00:00.000Z"
  },
  {
    "id": "dl-tag-330",
    "name": "DL标签330",
    "category": "DL",
    "description": "DL标签",
    "count": 0,
    "createdAt": "2026-07-02T00:00:00.000Z"
  },
  {
    "id": "dl-tag-331",
    "name": "DL标签331",
    "category": "DL",
    "description": "DL标签",
    "count": 0,
    "createdAt": "2026-07-02T00:00:00.000Z"
  },
  {
    "id": "dl-tag-332",
    "name": "DL标签332",
    "category": "DL",
    "description": "DL标签",
    "count": 0,
    "createdAt": "2026-07-02T00:00:00.000Z"
  },
  {
    "id": "dl-tag-333",
    "name": "DL标签333",
    "category": "DL",
    "description": "DL标签",
    "count": 0,
    "createdAt": "2026-07-02T00:00:00.000Z"
  },
  {
    "id": "dl-tag-334",
    "name": "DL标签334",
    "category": "DL",
    "description": "DL标签",
    "count": 0,
    "createdAt": "2026-07-02T00:00:00.000Z"
  },
  {
    "id": "dl-tag-335",
    "name": "DL标签335",
    "category": "DL",
    "description": "DL标签",
    "count": 0,
    "createdAt": "2026-07-02T00:00:00.000Z"
  },
  {
    "id": "dl-tag-336",
    "name": "DL标签336",
    "category": "DL",
    "description": "DL标签",
    "count": 0,
    "createdAt": "2026-07-02T00:00:00.000Z"
  },
  {
    "id": "dl-tag-337",
    "name": "DL标签337",
    "category": "DL",
    "description": "DL标签",
    "count": 0,
    "createdAt": "2026-07-02T00:00:00.000Z"
  },
  {
    "id": "dl-tag-338",
    "name": "DL标签338",
    "category": "DL",
    "description": "DL标签",
    "count": 0,
    "createdAt": "2026-07-02T00:00:00.000Z"
  },
  {
    "id": "dl-tag-339",
    "name": "DL标签339",
    "category": "DL",
    "description": "DL标签",
    "count": 0,
    "createdAt": "2026-07-02T00:00:00.000Z"
  },
  {
    "id": "dl-tag-340",
    "name": "DL标签340",
    "category": "DL",
    "description": "DL标签",
    "count": 0,
    "createdAt": "2026-07-02T00:00:00.000Z"
  },
  {
    "id": "dl-tag-341",
    "name": "DL标签341",
    "category": "DL",
    "description": "DL标签",
    "count": 0,
    "createdAt": "2026-07-02T00:00:00.000Z"
  },
  {
    "id": "dl-tag-342",
    "name": "DL标签342",
    "category": "DL",
    "description": "DL标签",
    "count": 0,
    "createdAt": "2026-07-02T00:00:00.000Z"
  },
  {
    "id": "dl-tag-343",
    "name": "DL标签343",
    "category": "DL",
    "description": "DL标签",
    "count": 0,
    "createdAt": "2026-07-02T00:00:00.000Z"
  },
  {
    "id": "dl-tag-344",
    "name": "DL标签344",
    "category": "DL",
    "description": "DL标签",
    "count": 0,
    "createdAt": "2026-07-02T00:00:00.000Z"
  },
  {
    "id": "dl-tag-345",
    "name": "DL标签345",
    "category": "DL",
    "description": "DL标签",
    "count": 0,
    "createdAt": "2026-07-02T00:00:00.000Z"
  },
  {
    "id": "dl-tag-346",
    "name": "DL标签346",
    "category": "DL",
    "description": "DL标签",
    "count": 0,
    "createdAt": "2026-07-02T00:00:00.000Z"
  },
  {
    "id": "dl-tag-347",
    "name": "DL标签347",
    "category": "DL",
    "description": "DL标签",
    "count": 0,
    "createdAt": "2026-07-02T00:00:00.000Z"
  },
  {
    "id": "dl-tag-348",
    "name": "DL标签348",
    "category": "DL",
    "description": "DL标签",
    "count": 0,
    "createdAt": "2026-07-02T00:00:00.000Z"
  },
  {
    "id": "dl-tag-349",
    "name": "DL标签349",
    "category": "DL",
    "description": "DL标签",
    "count": 0,
    "createdAt": "2026-07-02T00:00:00.000Z"
  },
  {
    "id": "dl-tag-350",
    "name": "DL标签350",
    "category": "DL",
    "description": "DL标签",
    "count": 0,
    "createdAt": "2026-07-02T00:00:00.000Z"
  },
  {
    "id": "dl-tag-351",
    "name": "DL标签351",
    "category": "DL",
    "description": "DL标签",
    "count": 0,
    "createdAt": "2026-07-02T00:00:00.000Z"
  },
  {
    "id": "dl-tag-352",
    "name": "DL标签352",
    "category": "DL",
    "description": "DL标签",
    "count": 0,
    "createdAt": "2026-07-02T00:00:00.000Z"
  },
  {
    "id": "dl-tag-353",
    "name": "DL标签353",
    "category": "DL",
    "description": "DL标签",
    "count": 0,
    "createdAt": "2026-07-02T00:00:00.000Z"
  },
  {
    "id": "dl-tag-354",
    "name": "DL标签354",
    "category": "DL",
    "description": "DL标签",
    "count": 0,
    "createdAt": "2026-07-02T00:00:00.000Z"
  },
  {
    "id": "dl-tag-355",
    "name": "DL标签355",
    "category": "DL",
    "description": "DL标签",
    "count": 0,
    "createdAt": "2026-07-02T00:00:00.000Z"
  },
  {
    "id": "dl-tag-356",
    "name": "DL标签356",
    "category": "DL",
    "description": "DL标签",
    "count": 0,
    "createdAt": "2026-07-02T00:00:00.000Z"
  },
  {
    "id": "dl-tag-357",
    "name": "DL标签357",
    "category": "DL",
    "description": "DL标签",
    "count": 0,
    "createdAt": "2026-07-02T00:00:00.000Z"
  },
  {
    "id": "dl-tag-358",
    "name": "DL标签358",
    "category": "DL",
    "description": "DL标签",
    "count": 0,
    "createdAt": "2026-07-02T00:00:00.000Z"
  },
  {
    "id": "dl-tag-359",
    "name": "DL标签359",
    "category": "DL",
    "description": "DL标签",
    "count": 0,
    "createdAt": "2026-07-02T00:00:00.000Z"
  },
  {
    "id": "dl-tag-360",
    "name": "DL标签360",
    "category": "DL",
    "description": "DL标签",
    "count": 0,
    "createdAt": "2026-07-02T00:00:00.000Z"
  },
  {
    "id": "dl-tag-361",
    "name": "DL标签361",
    "category": "DL",
    "description": "DL标签",
    "count": 0,
    "createdAt": "2026-07-02T00:00:00.000Z"
  }
]